<?xml version="1.0" encoding="UTF-8"?>
<votes>
	<vote>
		<voteinfo>
			http://www.itsyourparliament.eu/api/vote.php?id=310&amp;key=0		</voteinfo>
		<voteid>
			310
		</voteid>
	</vote>
	<vote>
		<voteinfo>
			http://www.itsyourparliament.eu/api/vote.php?id=311&amp;key=0		</voteinfo>
		<voteid>
			311
		</voteid>
	</vote>
	<vote>
		<voteinfo>
			http://www.itsyourparliament.eu/api/vote.php?id=312&amp;key=0		</voteinfo>
		<voteid>
			312
		</voteid>
	</vote>
	<vote>
		<voteinfo>
			http://www.itsyourparliament.eu/api/vote.php?id=313&amp;key=0		</voteinfo>
		<voteid>
			313
		</voteid>
	</vote>
	<vote>
		<voteinfo>
			http://www.itsyourparliament.eu/api/vote.php?id=314&amp;key=0		</voteinfo>
		<voteid>
			314
		</voteid>
	</vote>
	<vote>
		<voteinfo>
			http://www.itsyourparliament.eu/api/vote.php?id=315&amp;key=0		</voteinfo>
		<voteid>
			315
		</voteid>
	</vote>
	<vote>
		<voteinfo>
			http://www.itsyourparliament.eu/api/vote.php?id=316&amp;key=0		</voteinfo>
		<voteid>
			316
		</voteid>
	</vote>
	<vote>
		<voteinfo>
			http://www.itsyourparliament.eu/api/vote.php?id=317&amp;key=0		</voteinfo>
		<voteid>
			317
		</voteid>
	</vote>
	<vote>
		<voteinfo>
			http://www.itsyourparliament.eu/api/vote.php?id=318&amp;key=0		</voteinfo>
		<voteid>
			318
		</voteid>
	</vote>
	<vote>
		<voteinfo>
			http://www.itsyourparliament.eu/api/vote.php?id=319&amp;key=0		</voteinfo>
		<voteid>
			319
		</voteid>
	</vote>
	<vote>
		<voteinfo>
			http://www.itsyourparliament.eu/api/vote.php?id=320&amp;key=0		</voteinfo>
		<voteid>
			320
		</voteid>
	</vote>
	<vote>
		<voteinfo>
			http://www.itsyourparliament.eu/api/vote.php?id=321&amp;key=0		</voteinfo>
		<voteid>
			321
		</voteid>
	</vote>
	<vote>
		<voteinfo>
			http://www.itsyourparliament.eu/api/vote.php?id=439&amp;key=0		</voteinfo>
		<voteid>
			439
		</voteid>
	</vote>
	<vote>
		<voteinfo>
			http://www.itsyourparliament.eu/api/vote.php?id=772&amp;key=0		</voteinfo>
		<voteid>
			772
		</voteid>
	</vote>
	<vote>
		<voteinfo>
			http://www.itsyourparliament.eu/api/vote.php?id=773&amp;key=0		</voteinfo>
		<voteid>
			773
		</voteid>
	</vote>
	<vote>
		<voteinfo>
			http://www.itsyourparliament.eu/api/vote.php?id=942&amp;key=0		</voteinfo>
		<voteid>
			942
		</voteid>
	</vote>
	<vote>
		<voteinfo>
			http://www.itsyourparliament.eu/api/vote.php?id=943&amp;key=0		</voteinfo>
		<voteid>
			943
		</voteid>
	</vote>
	<vote>
		<voteinfo>
			http://www.itsyourparliament.eu/api/vote.php?id=944&amp;key=0		</voteinfo>
		<voteid>
			944
		</voteid>
	</vote>
	<vote>
		<voteinfo>
			http://www.itsyourparliament.eu/api/vote.php?id=945&amp;key=0		</voteinfo>
		<voteid>
			945
		</voteid>
	</vote>
	<vote>
		<voteinfo>
			http://www.itsyourparliament.eu/api/vote.php?id=946&amp;key=0		</voteinfo>
		<voteid>
			946
		</voteid>
	</vote>
	<vote>
		<voteinfo>
			http://www.itsyourparliament.eu/api/vote.php?id=947&amp;key=0		</voteinfo>
		<voteid>
			947
		</voteid>
	</vote>
	<vote>
		<voteinfo>
			http://www.itsyourparliament.eu/api/vote.php?id=948&amp;key=0		</voteinfo>
		<voteid>
			948
		</voteid>
	</vote>
	<vote>
		<voteinfo>
			http://www.itsyourparliament.eu/api/vote.php?id=949&amp;key=0		</voteinfo>
		<voteid>
			949
		</voteid>
	</vote>
	<vote>
		<voteinfo>
			http://www.itsyourparliament.eu/api/vote.php?id=950&amp;key=0		</voteinfo>
		<voteid>
			950
		</voteid>
	</vote>
	<vote>
		<voteinfo>
			http://www.itsyourparliament.eu/api/vote.php?id=951&amp;key=0		</voteinfo>
		<voteid>
			951
		</voteid>
	</vote>
	<vote>
		<voteinfo>
			http://www.itsyourparliament.eu/api/vote.php?id=952&amp;key=0		</voteinfo>
		<voteid>
			952
		</voteid>
	</vote>
	<vote>
		<voteinfo>
			http://www.itsyourparliament.eu/api/vote.php?id=953&amp;key=0		</voteinfo>
		<voteid>
			953
		</voteid>
	</vote>
	<vote>
		<voteinfo>
			http://www.itsyourparliament.eu/api/vote.php?id=954&amp;key=0		</voteinfo>
		<voteid>
			954
		</voteid>
	</vote>
	<vote>
		<voteinfo>
			http://www.itsyourparliament.eu/api/vote.php?id=955&amp;key=0		</voteinfo>
		<voteid>
			955
		</voteid>
	</vote>
	<vote>
		<voteinfo>
			http://www.itsyourparliament.eu/api/vote.php?id=956&amp;key=0		</voteinfo>
		<voteid>
			956
		</voteid>
	</vote>
	<vote>
		<voteinfo>
			http://www.itsyourparliament.eu/api/vote.php?id=957&amp;key=0		</voteinfo>
		<voteid>
			957
		</voteid>
	</vote>
	<vote>
		<voteinfo>
			http://www.itsyourparliament.eu/api/vote.php?id=958&amp;key=0		</voteinfo>
		<voteid>
			958
		</voteid>
	</vote>
	<vote>
		<voteinfo>
			http://www.itsyourparliament.eu/api/vote.php?id=1122&amp;key=0		</voteinfo>
		<voteid>
			1122
		</voteid>
	</vote>
	<vote>
		<voteinfo>
			http://www.itsyourparliament.eu/api/vote.php?id=1157&amp;key=0		</voteinfo>
		<voteid>
			1157
		</voteid>
	</vote>
	<vote>
		<voteinfo>
			http://www.itsyourparliament.eu/api/vote.php?id=1158&amp;key=0		</voteinfo>
		<voteid>
			1158
		</voteid>
	</vote>
	<vote>
		<voteinfo>
			http://www.itsyourparliament.eu/api/vote.php?id=1159&amp;key=0		</voteinfo>
		<voteid>
			1159
		</voteid>
	</vote>
	<vote>
		<voteinfo>
			http://www.itsyourparliament.eu/api/vote.php?id=1160&amp;key=0		</voteinfo>
		<voteid>
			1160
		</voteid>
	</vote>
	<vote>
		<voteinfo>
			http://www.itsyourparliament.eu/api/vote.php?id=1161&amp;key=0		</voteinfo>
		<voteid>
			1161
		</voteid>
	</vote>
	<vote>
		<voteinfo>
			http://www.itsyourparliament.eu/api/vote.php?id=1162&amp;key=0		</voteinfo>
		<voteid>
			1162
		</voteid>
	</vote>
	<vote>
		<voteinfo>
			http://www.itsyourparliament.eu/api/vote.php?id=1163&amp;key=0		</voteinfo>
		<voteid>
			1163
		</voteid>
	</vote>
	<vote>
		<voteinfo>
			http://www.itsyourparliament.eu/api/vote.php?id=1164&amp;key=0		</voteinfo>
		<voteid>
			1164
		</voteid>
	</vote>
	<vote>
		<voteinfo>
			http://www.itsyourparliament.eu/api/vote.php?id=1165&amp;key=0		</voteinfo>
		<voteid>
			1165
		</voteid>
	</vote>
	<vote>
		<voteinfo>
			http://www.itsyourparliament.eu/api/vote.php?id=1166&amp;key=0		</voteinfo>
		<voteid>
			1166
		</voteid>
	</vote>
	<vote>
		<voteinfo>
			http://www.itsyourparliament.eu/api/vote.php?id=1167&amp;key=0		</voteinfo>
		<voteid>
			1167
		</voteid>
	</vote>
	<vote>
		<voteinfo>
			http://www.itsyourparliament.eu/api/vote.php?id=1168&amp;key=0		</voteinfo>
		<voteid>
			1168
		</voteid>
	</vote>
	<vote>
		<voteinfo>
			http://www.itsyourparliament.eu/api/vote.php?id=1169&amp;key=0		</voteinfo>
		<voteid>
			1169
		</voteid>
	</vote>
	<vote>
		<voteinfo>
			http://www.itsyourparliament.eu/api/vote.php?id=1170&amp;key=0		</voteinfo>
		<voteid>
			1170
		</voteid>
	</vote>
	<vote>
		<voteinfo>
			http://www.itsyourparliament.eu/api/vote.php?id=1171&amp;key=0		</voteinfo>
		<voteid>
			1171
		</voteid>
	</vote>
	<vote>
		<voteinfo>
			http://www.itsyourparliament.eu/api/vote.php?id=1172&amp;key=0		</voteinfo>
		<voteid>
			1172
		</voteid>
	</vote>
	<vote>
		<voteinfo>
			http://www.itsyourparliament.eu/api/vote.php?id=1173&amp;key=0		</voteinfo>
		<voteid>
			1173
		</voteid>
	</vote>
	<vote>
		<voteinfo>
			http://www.itsyourparliament.eu/api/vote.php?id=1174&amp;key=0		</voteinfo>
		<voteid>
			1174
		</voteid>
	</vote>
	<vote>
		<voteinfo>
			http://www.itsyourparliament.eu/api/vote.php?id=1175&amp;key=0		</voteinfo>
		<voteid>
			1175
		</voteid>
	</vote>
	<vote>
		<voteinfo>
			http://www.itsyourparliament.eu/api/vote.php?id=1480&amp;key=0		</voteinfo>
		<voteid>
			1480
		</voteid>
	</vote>
	<vote>
		<voteinfo>
			http://www.itsyourparliament.eu/api/vote.php?id=1481&amp;key=0		</voteinfo>
		<voteid>
			1481
		</voteid>
	</vote>
	<vote>
		<voteinfo>
			http://www.itsyourparliament.eu/api/vote.php?id=1482&amp;key=0		</voteinfo>
		<voteid>
			1482
		</voteid>
	</vote>
	<vote>
		<voteinfo>
			http://www.itsyourparliament.eu/api/vote.php?id=1483&amp;key=0		</voteinfo>
		<voteid>
			1483
		</voteid>
	</vote>
	<vote>
		<voteinfo>
			http://www.itsyourparliament.eu/api/vote.php?id=1484&amp;key=0		</voteinfo>
		<voteid>
			1484
		</voteid>
	</vote>
	<vote>
		<voteinfo>
			http://www.itsyourparliament.eu/api/vote.php?id=1485&amp;key=0		</voteinfo>
		<voteid>
			1485
		</voteid>
	</vote>
	<vote>
		<voteinfo>
			http://www.itsyourparliament.eu/api/vote.php?id=1486&amp;key=0		</voteinfo>
		<voteid>
			1486
		</voteid>
	</vote>
	<vote>
		<voteinfo>
			http://www.itsyourparliament.eu/api/vote.php?id=1487&amp;key=0		</voteinfo>
		<voteid>
			1487
		</voteid>
	</vote>
	<vote>
		<voteinfo>
			http://www.itsyourparliament.eu/api/vote.php?id=1488&amp;key=0		</voteinfo>
		<voteid>
			1488
		</voteid>
	</vote>
	<vote>
		<voteinfo>
			http://www.itsyourparliament.eu/api/vote.php?id=1489&amp;key=0		</voteinfo>
		<voteid>
			1489
		</voteid>
	</vote>
	<vote>
		<voteinfo>
			http://www.itsyourparliament.eu/api/vote.php?id=1490&amp;key=0		</voteinfo>
		<voteid>
			1490
		</voteid>
	</vote>
	<vote>
		<voteinfo>
			http://www.itsyourparliament.eu/api/vote.php?id=1491&amp;key=0		</voteinfo>
		<voteid>
			1491
		</voteid>
	</vote>
	<vote>
		<voteinfo>
			http://www.itsyourparliament.eu/api/vote.php?id=1492&amp;key=0		</voteinfo>
		<voteid>
			1492
		</voteid>
	</vote>
	<vote>
		<voteinfo>
			http://www.itsyourparliament.eu/api/vote.php?id=1493&amp;key=0		</voteinfo>
		<voteid>
			1493
		</voteid>
	</vote>
	<vote>
		<voteinfo>
			http://www.itsyourparliament.eu/api/vote.php?id=1494&amp;key=0		</voteinfo>
		<voteid>
			1494
		</voteid>
	</vote>
	<vote>
		<voteinfo>
			http://www.itsyourparliament.eu/api/vote.php?id=1495&amp;key=0		</voteinfo>
		<voteid>
			1495
		</voteid>
	</vote>
	<vote>
		<voteinfo>
			http://www.itsyourparliament.eu/api/vote.php?id=1525&amp;key=0		</voteinfo>
		<voteid>
			1525
		</voteid>
	</vote>
	<vote>
		<voteinfo>
			http://www.itsyourparliament.eu/api/vote.php?id=1873&amp;key=0		</voteinfo>
		<voteid>
			1873
		</voteid>
	</vote>
	<vote>
		<voteinfo>
			http://www.itsyourparliament.eu/api/vote.php?id=1874&amp;key=0		</voteinfo>
		<voteid>
			1874
		</voteid>
	</vote>
	<vote>
		<voteinfo>
			http://www.itsyourparliament.eu/api/vote.php?id=1885&amp;key=0		</voteinfo>
		<voteid>
			1885
		</voteid>
	</vote>
	<vote>
		<voteinfo>
			http://www.itsyourparliament.eu/api/vote.php?id=1886&amp;key=0		</voteinfo>
		<voteid>
			1886
		</voteid>
	</vote>
	<vote>
		<voteinfo>
			http://www.itsyourparliament.eu/api/vote.php?id=2297&amp;key=0		</voteinfo>
		<voteid>
			2297
		</voteid>
	</vote>
	<vote>
		<voteinfo>
			http://www.itsyourparliament.eu/api/vote.php?id=2298&amp;key=0		</voteinfo>
		<voteid>
			2298
		</voteid>
	</vote>
	<vote>
		<voteinfo>
			http://www.itsyourparliament.eu/api/vote.php?id=2299&amp;key=0		</voteinfo>
		<voteid>
			2299
		</voteid>
	</vote>
	<vote>
		<voteinfo>
			http://www.itsyourparliament.eu/api/vote.php?id=2300&amp;key=0		</voteinfo>
		<voteid>
			2300
		</voteid>
	</vote>
	<vote>
		<voteinfo>
			http://www.itsyourparliament.eu/api/vote.php?id=2332&amp;key=0		</voteinfo>
		<voteid>
			2332
		</voteid>
	</vote>
	<vote>
		<voteinfo>
			http://www.itsyourparliament.eu/api/vote.php?id=2440&amp;key=0		</voteinfo>
		<voteid>
			2440
		</voteid>
	</vote>
	<vote>
		<voteinfo>
			http://www.itsyourparliament.eu/api/vote.php?id=2471&amp;key=0		</voteinfo>
		<voteid>
			2471
		</voteid>
	</vote>
	<vote>
		<voteinfo>
			http://www.itsyourparliament.eu/api/vote.php?id=2472&amp;key=0		</voteinfo>
		<voteid>
			2472
		</voteid>
	</vote>
	<vote>
		<voteinfo>
			http://www.itsyourparliament.eu/api/vote.php?id=2473&amp;key=0		</voteinfo>
		<voteid>
			2473
		</voteid>
	</vote>
	<vote>
		<voteinfo>
			http://www.itsyourparliament.eu/api/vote.php?id=2812&amp;key=0		</voteinfo>
		<voteid>
			2812
		</voteid>
	</vote>
	<vote>
		<voteinfo>
			http://www.itsyourparliament.eu/api/vote.php?id=2813&amp;key=0		</voteinfo>
		<voteid>
			2813
		</voteid>
	</vote>
	<vote>
		<voteinfo>
			http://www.itsyourparliament.eu/api/vote.php?id=2858&amp;key=0		</voteinfo>
		<voteid>
			2858
		</voteid>
	</vote>
	<vote>
		<voteinfo>
			http://www.itsyourparliament.eu/api/vote.php?id=2863&amp;key=0		</voteinfo>
		<voteid>
			2863
		</voteid>
	</vote>
	<vote>
		<voteinfo>
			http://www.itsyourparliament.eu/api/vote.php?id=2864&amp;key=0		</voteinfo>
		<voteid>
			2864
		</voteid>
	</vote>
	<vote>
		<voteinfo>
			http://www.itsyourparliament.eu/api/vote.php?id=2865&amp;key=0		</voteinfo>
		<voteid>
			2865
		</voteid>
	</vote>
	<vote>
		<voteinfo>
			http://www.itsyourparliament.eu/api/vote.php?id=2866&amp;key=0		</voteinfo>
		<voteid>
			2866
		</voteid>
	</vote>
	<vote>
		<voteinfo>
			http://www.itsyourparliament.eu/api/vote.php?id=2930&amp;key=0		</voteinfo>
		<voteid>
			2930
		</voteid>
	</vote>
	<vote>
		<voteinfo>
			http://www.itsyourparliament.eu/api/vote.php?id=3003&amp;key=0		</voteinfo>
		<voteid>
			3003
		</voteid>
	</vote>
	<vote>
		<voteinfo>
			http://www.itsyourparliament.eu/api/vote.php?id=3032&amp;key=0		</voteinfo>
		<voteid>
			3032
		</voteid>
	</vote>
	<vote>
		<voteinfo>
			http://www.itsyourparliament.eu/api/vote.php?id=3991&amp;key=0		</voteinfo>
		<voteid>
			3991
		</voteid>
	</vote>
	<vote>
		<voteinfo>
			http://www.itsyourparliament.eu/api/vote.php?id=3992&amp;key=0		</voteinfo>
		<voteid>
			3992
		</voteid>
	</vote>
	<vote>
		<voteinfo>
			http://www.itsyourparliament.eu/api/vote.php?id=3993&amp;key=0		</voteinfo>
		<voteid>
			3993
		</voteid>
	</vote>
	<vote>
		<voteinfo>
			http://www.itsyourparliament.eu/api/vote.php?id=3994&amp;key=0		</voteinfo>
		<voteid>
			3994
		</voteid>
	</vote>
	<vote>
		<voteinfo>
			http://www.itsyourparliament.eu/api/vote.php?id=3995&amp;key=0		</voteinfo>
		<voteid>
			3995
		</voteid>
	</vote>
	<vote>
		<voteinfo>
			http://www.itsyourparliament.eu/api/vote.php?id=3996&amp;key=0		</voteinfo>
		<voteid>
			3996
		</voteid>
	</vote>
	<vote>
		<voteinfo>
			http://www.itsyourparliament.eu/api/vote.php?id=3997&amp;key=0		</voteinfo>
		<voteid>
			3997
		</voteid>
	</vote>
	<vote>
		<voteinfo>
			http://www.itsyourparliament.eu/api/vote.php?id=3998&amp;key=0		</voteinfo>
		<voteid>
			3998
		</voteid>
	</vote>
	<vote>
		<voteinfo>
			http://www.itsyourparliament.eu/api/vote.php?id=3999&amp;key=0		</voteinfo>
		<voteid>
			3999
		</voteid>
	</vote>
	<vote>
		<voteinfo>
			http://www.itsyourparliament.eu/api/vote.php?id=4000&amp;key=0		</voteinfo>
		<voteid>
			4000
		</voteid>
	</vote>
	<vote>
		<voteinfo>
			http://www.itsyourparliament.eu/api/vote.php?id=4001&amp;key=0		</voteinfo>
		<voteid>
			4001
		</voteid>
	</vote>
	<vote>
		<voteinfo>
			http://www.itsyourparliament.eu/api/vote.php?id=4002&amp;key=0		</voteinfo>
		<voteid>
			4002
		</voteid>
	</vote>
	<vote>
		<voteinfo>
			http://www.itsyourparliament.eu/api/vote.php?id=4069&amp;key=0		</voteinfo>
		<voteid>
			4069
		</voteid>
	</vote>
	<vote>
		<voteinfo>
			http://www.itsyourparliament.eu/api/vote.php?id=4127&amp;key=0		</voteinfo>
		<voteid>
			4127
		</voteid>
	</vote>
	<vote>
		<voteinfo>
			http://www.itsyourparliament.eu/api/vote.php?id=4128&amp;key=0		</voteinfo>
		<voteid>
			4128
		</voteid>
	</vote>
	<vote>
		<voteinfo>
			http://www.itsyourparliament.eu/api/vote.php?id=4129&amp;key=0		</voteinfo>
		<voteid>
			4129
		</voteid>
	</vote>
	<vote>
		<voteinfo>
			http://www.itsyourparliament.eu/api/vote.php?id=4130&amp;key=0		</voteinfo>
		<voteid>
			4130
		</voteid>
	</vote>
	<vote>
		<voteinfo>
			http://www.itsyourparliament.eu/api/vote.php?id=4131&amp;key=0		</voteinfo>
		<voteid>
			4131
		</voteid>
	</vote>
	<vote>
		<voteinfo>
			http://www.itsyourparliament.eu/api/vote.php?id=4132&amp;key=0		</voteinfo>
		<voteid>
			4132
		</voteid>
	</vote>
	<vote>
		<voteinfo>
			http://www.itsyourparliament.eu/api/vote.php?id=4133&amp;key=0		</voteinfo>
		<voteid>
			4133
		</voteid>
	</vote>
	<vote>
		<voteinfo>
			http://www.itsyourparliament.eu/api/vote.php?id=4134&amp;key=0		</voteinfo>
		<voteid>
			4134
		</voteid>
	</vote>
	<vote>
		<voteinfo>
			http://www.itsyourparliament.eu/api/vote.php?id=4161&amp;key=0		</voteinfo>
		<voteid>
			4161
		</voteid>
	</vote>
	<vote>
		<voteinfo>
			http://www.itsyourparliament.eu/api/vote.php?id=4162&amp;key=0		</voteinfo>
		<voteid>
			4162
		</voteid>
	</vote>
	<vote>
		<voteinfo>
			http://www.itsyourparliament.eu/api/vote.php?id=4163&amp;key=0		</voteinfo>
		<voteid>
			4163
		</voteid>
	</vote>
	<vote>
		<voteinfo>
			http://www.itsyourparliament.eu/api/vote.php?id=4164&amp;key=0		</voteinfo>
		<voteid>
			4164
		</voteid>
	</vote>
	<vote>
		<voteinfo>
			http://www.itsyourparliament.eu/api/vote.php?id=4165&amp;key=0		</voteinfo>
		<voteid>
			4165
		</voteid>
	</vote>
	<vote>
		<voteinfo>
			http://www.itsyourparliament.eu/api/vote.php?id=4166&amp;key=0		</voteinfo>
		<voteid>
			4166
		</voteid>
	</vote>
	<vote>
		<voteinfo>
			http://www.itsyourparliament.eu/api/vote.php?id=4167&amp;key=0		</voteinfo>
		<voteid>
			4167
		</voteid>
	</vote>
	<vote>
		<voteinfo>
			http://www.itsyourparliament.eu/api/vote.php?id=4168&amp;key=0		</voteinfo>
		<voteid>
			4168
		</voteid>
	</vote>
	<vote>
		<voteinfo>
			http://www.itsyourparliament.eu/api/vote.php?id=4169&amp;key=0		</voteinfo>
		<voteid>
			4169
		</voteid>
	</vote>
	<vote>
		<voteinfo>
			http://www.itsyourparliament.eu/api/vote.php?id=4170&amp;key=0		</voteinfo>
		<voteid>
			4170
		</voteid>
	</vote>
	<vote>
		<voteinfo>
			http://www.itsyourparliament.eu/api/vote.php?id=4171&amp;key=0		</voteinfo>
		<voteid>
			4171
		</voteid>
	</vote>
	<vote>
		<voteinfo>
			http://www.itsyourparliament.eu/api/vote.php?id=4172&amp;key=0		</voteinfo>
		<voteid>
			4172
		</voteid>
	</vote>
	<vote>
		<voteinfo>
			http://www.itsyourparliament.eu/api/vote.php?id=4173&amp;key=0		</voteinfo>
		<voteid>
			4173
		</voteid>
	</vote>
	<vote>
		<voteinfo>
			http://www.itsyourparliament.eu/api/vote.php?id=4174&amp;key=0		</voteinfo>
		<voteid>
			4174
		</voteid>
	</vote>
	<vote>
		<voteinfo>
			http://www.itsyourparliament.eu/api/vote.php?id=4175&amp;key=0		</voteinfo>
		<voteid>
			4175
		</voteid>
	</vote>
	<vote>
		<voteinfo>
			http://www.itsyourparliament.eu/api/vote.php?id=4176&amp;key=0		</voteinfo>
		<voteid>
			4176
		</voteid>
	</vote>
	<vote>
		<voteinfo>
			http://www.itsyourparliament.eu/api/vote.php?id=4177&amp;key=0		</voteinfo>
		<voteid>
			4177
		</voteid>
	</vote>
	<vote>
		<voteinfo>
			http://www.itsyourparliament.eu/api/vote.php?id=4178&amp;key=0		</voteinfo>
		<voteid>
			4178
		</voteid>
	</vote>
	<vote>
		<voteinfo>
			http://www.itsyourparliament.eu/api/vote.php?id=4443&amp;key=0		</voteinfo>
		<voteid>
			4443
		</voteid>
	</vote>
	<vote>
		<voteinfo>
			http://www.itsyourparliament.eu/api/vote.php?id=4444&amp;key=0		</voteinfo>
		<voteid>
			4444
		</voteid>
	</vote>
	<vote>
		<voteinfo>
			http://www.itsyourparliament.eu/api/vote.php?id=4445&amp;key=0		</voteinfo>
		<voteid>
			4445
		</voteid>
	</vote>
	<vote>
		<voteinfo>
			http://www.itsyourparliament.eu/api/vote.php?id=4446&amp;key=0		</voteinfo>
		<voteid>
			4446
		</voteid>
	</vote>
	<vote>
		<voteinfo>
			http://www.itsyourparliament.eu/api/vote.php?id=4447&amp;key=0		</voteinfo>
		<voteid>
			4447
		</voteid>
	</vote>
	<vote>
		<voteinfo>
			http://www.itsyourparliament.eu/api/vote.php?id=4448&amp;key=0		</voteinfo>
		<voteid>
			4448
		</voteid>
	</vote>
	<vote>
		<voteinfo>
			http://www.itsyourparliament.eu/api/vote.php?id=4449&amp;key=0		</voteinfo>
		<voteid>
			4449
		</voteid>
	</vote>
	<vote>
		<voteinfo>
			http://www.itsyourparliament.eu/api/vote.php?id=4450&amp;key=0		</voteinfo>
		<voteid>
			4450
		</voteid>
	</vote>
	<vote>
		<voteinfo>
			http://www.itsyourparliament.eu/api/vote.php?id=4451&amp;key=0		</voteinfo>
		<voteid>
			4451
		</voteid>
	</vote>
	<vote>
		<voteinfo>
			http://www.itsyourparliament.eu/api/vote.php?id=4452&amp;key=0		</voteinfo>
		<voteid>
			4452
		</voteid>
	</vote>
	<vote>
		<voteinfo>
			http://www.itsyourparliament.eu/api/vote.php?id=4453&amp;key=0		</voteinfo>
		<voteid>
			4453
		</voteid>
	</vote>
	<vote>
		<voteinfo>
			http://www.itsyourparliament.eu/api/vote.php?id=4454&amp;key=0		</voteinfo>
		<voteid>
			4454
		</voteid>
	</vote>
	<vote>
		<voteinfo>
			http://www.itsyourparliament.eu/api/vote.php?id=4455&amp;key=0		</voteinfo>
		<voteid>
			4455
		</voteid>
	</vote>
	<vote>
		<voteinfo>
			http://www.itsyourparliament.eu/api/vote.php?id=4456&amp;key=0		</voteinfo>
		<voteid>
			4456
		</voteid>
	</vote>
	<vote>
		<voteinfo>
			http://www.itsyourparliament.eu/api/vote.php?id=4457&amp;key=0		</voteinfo>
		<voteid>
			4457
		</voteid>
	</vote>
	<vote>
		<voteinfo>
			http://www.itsyourparliament.eu/api/vote.php?id=4458&amp;key=0		</voteinfo>
		<voteid>
			4458
		</voteid>
	</vote>
	<vote>
		<voteinfo>
			http://www.itsyourparliament.eu/api/vote.php?id=4459&amp;key=0		</voteinfo>
		<voteid>
			4459
		</voteid>
	</vote>
	<vote>
		<voteinfo>
			http://www.itsyourparliament.eu/api/vote.php?id=4460&amp;key=0		</voteinfo>
		<voteid>
			4460
		</voteid>
	</vote>
	<vote>
		<voteinfo>
			http://www.itsyourparliament.eu/api/vote.php?id=4584&amp;key=0		</voteinfo>
		<voteid>
			4584
		</voteid>
	</vote>
	<vote>
		<voteinfo>
			http://www.itsyourparliament.eu/api/vote.php?id=4585&amp;key=0		</voteinfo>
		<voteid>
			4585
		</voteid>
	</vote>
	<vote>
		<voteinfo>
			http://www.itsyourparliament.eu/api/vote.php?id=4586&amp;key=0		</voteinfo>
		<voteid>
			4586
		</voteid>
	</vote>
	<vote>
		<voteinfo>
			http://www.itsyourparliament.eu/api/vote.php?id=4587&amp;key=0		</voteinfo>
		<voteid>
			4587
		</voteid>
	</vote>
	<vote>
		<voteinfo>
			http://www.itsyourparliament.eu/api/vote.php?id=4588&amp;key=0		</voteinfo>
		<voteid>
			4588
		</voteid>
	</vote>
	<vote>
		<voteinfo>
			http://www.itsyourparliament.eu/api/vote.php?id=4589&amp;key=0		</voteinfo>
		<voteid>
			4589
		</voteid>
	</vote>
	<vote>
		<voteinfo>
			http://www.itsyourparliament.eu/api/vote.php?id=4590&amp;key=0		</voteinfo>
		<voteid>
			4590
		</voteid>
	</vote>
	<vote>
		<voteinfo>
			http://www.itsyourparliament.eu/api/vote.php?id=4591&amp;key=0		</voteinfo>
		<voteid>
			4591
		</voteid>
	</vote>
	<vote>
		<voteinfo>
			http://www.itsyourparliament.eu/api/vote.php?id=4592&amp;key=0		</voteinfo>
		<voteid>
			4592
		</voteid>
	</vote>
	<vote>
		<voteinfo>
			http://www.itsyourparliament.eu/api/vote.php?id=4593&amp;key=0		</voteinfo>
		<voteid>
			4593
		</voteid>
	</vote>
	<vote>
		<voteinfo>
			http://www.itsyourparliament.eu/api/vote.php?id=4594&amp;key=0		</voteinfo>
		<voteid>
			4594
		</voteid>
	</vote>
	<vote>
		<voteinfo>
			http://www.itsyourparliament.eu/api/vote.php?id=4595&amp;key=0		</voteinfo>
		<voteid>
			4595
		</voteid>
	</vote>
	<vote>
		<voteinfo>
			http://www.itsyourparliament.eu/api/vote.php?id=4596&amp;key=0		</voteinfo>
		<voteid>
			4596
		</voteid>
	</vote>
	<vote>
		<voteinfo>
			http://www.itsyourparliament.eu/api/vote.php?id=4597&amp;key=0		</voteinfo>
		<voteid>
			4597
		</voteid>
	</vote>
	<vote>
		<voteinfo>
			http://www.itsyourparliament.eu/api/vote.php?id=4598&amp;key=0		</voteinfo>
		<voteid>
			4598
		</voteid>
	</vote>
	<vote>
		<voteinfo>
			http://www.itsyourparliament.eu/api/vote.php?id=4599&amp;key=0		</voteinfo>
		<voteid>
			4599
		</voteid>
	</vote>
	<vote>
		<voteinfo>
			http://www.itsyourparliament.eu/api/vote.php?id=4600&amp;key=0		</voteinfo>
		<voteid>
			4600
		</voteid>
	</vote>
	<vote>
		<voteinfo>
			http://www.itsyourparliament.eu/api/vote.php?id=4601&amp;key=0		</voteinfo>
		<voteid>
			4601
		</voteid>
	</vote>
	<vote>
		<voteinfo>
			http://www.itsyourparliament.eu/api/vote.php?id=4602&amp;key=0		</voteinfo>
		<voteid>
			4602
		</voteid>
	</vote>
	<vote>
		<voteinfo>
			http://www.itsyourparliament.eu/api/vote.php?id=4603&amp;key=0		</voteinfo>
		<voteid>
			4603
		</voteid>
	</vote>
	<vote>
		<voteinfo>
			http://www.itsyourparliament.eu/api/vote.php?id=4604&amp;key=0		</voteinfo>
		<voteid>
			4604
		</voteid>
	</vote>
	<vote>
		<voteinfo>
			http://www.itsyourparliament.eu/api/vote.php?id=4605&amp;key=0		</voteinfo>
		<voteid>
			4605
		</voteid>
	</vote>
	<vote>
		<voteinfo>
			http://www.itsyourparliament.eu/api/vote.php?id=4678&amp;key=0		</voteinfo>
		<voteid>
			4678
		</voteid>
	</vote>
	<vote>
		<voteinfo>
			http://www.itsyourparliament.eu/api/vote.php?id=4697&amp;key=0		</voteinfo>
		<voteid>
			4697
		</voteid>
	</vote>
	<vote>
		<voteinfo>
			http://www.itsyourparliament.eu/api/vote.php?id=4698&amp;key=0		</voteinfo>
		<voteid>
			4698
		</voteid>
	</vote>
	<vote>
		<voteinfo>
			http://www.itsyourparliament.eu/api/vote.php?id=4699&amp;key=0		</voteinfo>
		<voteid>
			4699
		</voteid>
	</vote>
	<vote>
		<voteinfo>
			http://www.itsyourparliament.eu/api/vote.php?id=4700&amp;key=0		</voteinfo>
		<voteid>
			4700
		</voteid>
	</vote>
	<vote>
		<voteinfo>
			http://www.itsyourparliament.eu/api/vote.php?id=4701&amp;key=0		</voteinfo>
		<voteid>
			4701
		</voteid>
	</vote>
	<vote>
		<voteinfo>
			http://www.itsyourparliament.eu/api/vote.php?id=4702&amp;key=0		</voteinfo>
		<voteid>
			4702
		</voteid>
	</vote>
	<vote>
		<voteinfo>
			http://www.itsyourparliament.eu/api/vote.php?id=4703&amp;key=0		</voteinfo>
		<voteid>
			4703
		</voteid>
	</vote>
	<vote>
		<voteinfo>
			http://www.itsyourparliament.eu/api/vote.php?id=4704&amp;key=0		</voteinfo>
		<voteid>
			4704
		</voteid>
	</vote>
	<vote>
		<voteinfo>
			http://www.itsyourparliament.eu/api/vote.php?id=4705&amp;key=0		</voteinfo>
		<voteid>
			4705
		</voteid>
	</vote>
	<vote>
		<voteinfo>
			http://www.itsyourparliament.eu/api/vote.php?id=4706&amp;key=0		</voteinfo>
		<voteid>
			4706
		</voteid>
	</vote>
	<vote>
		<voteinfo>
			http://www.itsyourparliament.eu/api/vote.php?id=4707&amp;key=0		</voteinfo>
		<voteid>
			4707
		</voteid>
	</vote>
	<vote>
		<voteinfo>
			http://www.itsyourparliament.eu/api/vote.php?id=4708&amp;key=0		</voteinfo>
		<voteid>
			4708
		</voteid>
	</vote>
	<vote>
		<voteinfo>
			http://www.itsyourparliament.eu/api/vote.php?id=4709&amp;key=0		</voteinfo>
		<voteid>
			4709
		</voteid>
	</vote>
	<vote>
		<voteinfo>
			http://www.itsyourparliament.eu/api/vote.php?id=4710&amp;key=0		</voteinfo>
		<voteid>
			4710
		</voteid>
	</vote>
	<vote>
		<voteinfo>
			http://www.itsyourparliament.eu/api/vote.php?id=4711&amp;key=0		</voteinfo>
		<voteid>
			4711
		</voteid>
	</vote>
	<vote>
		<voteinfo>
			http://www.itsyourparliament.eu/api/vote.php?id=4712&amp;key=0		</voteinfo>
		<voteid>
			4712
		</voteid>
	</vote>
	<vote>
		<voteinfo>
			http://www.itsyourparliament.eu/api/vote.php?id=4713&amp;key=0		</voteinfo>
		<voteid>
			4713
		</voteid>
	</vote>
	<vote>
		<voteinfo>
			http://www.itsyourparliament.eu/api/vote.php?id=4714&amp;key=0		</voteinfo>
		<voteid>
			4714
		</voteid>
	</vote>
	<vote>
		<voteinfo>
			http://www.itsyourparliament.eu/api/vote.php?id=4715&amp;key=0		</voteinfo>
		<voteid>
			4715
		</voteid>
	</vote>
	<vote>
		<voteinfo>
			http://www.itsyourparliament.eu/api/vote.php?id=4716&amp;key=0		</voteinfo>
		<voteid>
			4716
		</voteid>
	</vote>
	<vote>
		<voteinfo>
			http://www.itsyourparliament.eu/api/vote.php?id=4717&amp;key=0		</voteinfo>
		<voteid>
			4717
		</voteid>
	</vote>
	<vote>
		<voteinfo>
			http://www.itsyourparliament.eu/api/vote.php?id=4718&amp;key=0		</voteinfo>
		<voteid>
			4718
		</voteid>
	</vote>
	<vote>
		<voteinfo>
			http://www.itsyourparliament.eu/api/vote.php?id=4719&amp;key=0		</voteinfo>
		<voteid>
			4719
		</voteid>
	</vote>
	<vote>
		<voteinfo>
			http://www.itsyourparliament.eu/api/vote.php?id=4720&amp;key=0		</voteinfo>
		<voteid>
			4720
		</voteid>
	</vote>
	<vote>
		<voteinfo>
			http://www.itsyourparliament.eu/api/vote.php?id=4721&amp;key=0		</voteinfo>
		<voteid>
			4721
		</voteid>
	</vote>
	<vote>
		<voteinfo>
			http://www.itsyourparliament.eu/api/vote.php?id=4722&amp;key=0		</voteinfo>
		<voteid>
			4722
		</voteid>
	</vote>
	<vote>
		<voteinfo>
			http://www.itsyourparliament.eu/api/vote.php?id=4728&amp;key=0		</voteinfo>
		<voteid>
			4728
		</voteid>
	</vote>
	<vote>
		<voteinfo>
			http://www.itsyourparliament.eu/api/vote.php?id=4729&amp;key=0		</voteinfo>
		<voteid>
			4729
		</voteid>
	</vote>
	<vote>
		<voteinfo>
			http://www.itsyourparliament.eu/api/vote.php?id=4730&amp;key=0		</voteinfo>
		<voteid>
			4730
		</voteid>
	</vote>
	<vote>
		<voteinfo>
			http://www.itsyourparliament.eu/api/vote.php?id=5010&amp;key=0		</voteinfo>
		<voteid>
			5010
		</voteid>
	</vote>
	<vote>
		<voteinfo>
			http://www.itsyourparliament.eu/api/vote.php?id=5011&amp;key=0		</voteinfo>
		<voteid>
			5011
		</voteid>
	</vote>
	<vote>
		<voteinfo>
			http://www.itsyourparliament.eu/api/vote.php?id=5012&amp;key=0		</voteinfo>
		<voteid>
			5012
		</voteid>
	</vote>
	<vote>
		<voteinfo>
			http://www.itsyourparliament.eu/api/vote.php?id=5013&amp;key=0		</voteinfo>
		<voteid>
			5013
		</voteid>
	</vote>
	<vote>
		<voteinfo>
			http://www.itsyourparliament.eu/api/vote.php?id=5014&amp;key=0		</voteinfo>
		<voteid>
			5014
		</voteid>
	</vote>
	<vote>
		<voteinfo>
			http://www.itsyourparliament.eu/api/vote.php?id=5015&amp;key=0		</voteinfo>
		<voteid>
			5015
		</voteid>
	</vote>
	<vote>
		<voteinfo>
			http://www.itsyourparliament.eu/api/vote.php?id=5016&amp;key=0		</voteinfo>
		<voteid>
			5016
		</voteid>
	</vote>
	<vote>
		<voteinfo>
			http://www.itsyourparliament.eu/api/vote.php?id=5017&amp;key=0		</voteinfo>
		<voteid>
			5017
		</voteid>
	</vote>
	<vote>
		<voteinfo>
			http://www.itsyourparliament.eu/api/vote.php?id=5018&amp;key=0		</voteinfo>
		<voteid>
			5018
		</voteid>
	</vote>
	<vote>
		<voteinfo>
			http://www.itsyourparliament.eu/api/vote.php?id=5019&amp;key=0		</voteinfo>
		<voteid>
			5019
		</voteid>
	</vote>
	<vote>
		<voteinfo>
			http://www.itsyourparliament.eu/api/vote.php?id=5020&amp;key=0		</voteinfo>
		<voteid>
			5020
		</voteid>
	</vote>
	<vote>
		<voteinfo>
			http://www.itsyourparliament.eu/api/vote.php?id=5021&amp;key=0		</voteinfo>
		<voteid>
			5021
		</voteid>
	</vote>
	<vote>
		<voteinfo>
			http://www.itsyourparliament.eu/api/vote.php?id=5022&amp;key=0		</voteinfo>
		<voteid>
			5022
		</voteid>
	</vote>
	<vote>
		<voteinfo>
			http://www.itsyourparliament.eu/api/vote.php?id=5023&amp;key=0		</voteinfo>
		<voteid>
			5023
		</voteid>
	</vote>
	<vote>
		<voteinfo>
			http://www.itsyourparliament.eu/api/vote.php?id=5146&amp;key=0		</voteinfo>
		<voteid>
			5146
		</voteid>
	</vote>
	<vote>
		<voteinfo>
			http://www.itsyourparliament.eu/api/vote.php?id=5147&amp;key=0		</voteinfo>
		<voteid>
			5147
		</voteid>
	</vote>
	<vote>
		<voteinfo>
			http://www.itsyourparliament.eu/api/vote.php?id=5148&amp;key=0		</voteinfo>
		<voteid>
			5148
		</voteid>
	</vote>
	<vote>
		<voteinfo>
			http://www.itsyourparliament.eu/api/vote.php?id=5149&amp;key=0		</voteinfo>
		<voteid>
			5149
		</voteid>
	</vote>
	<vote>
		<voteinfo>
			http://www.itsyourparliament.eu/api/vote.php?id=5150&amp;key=0		</voteinfo>
		<voteid>
			5150
		</voteid>
	</vote>
	<vote>
		<voteinfo>
			http://www.itsyourparliament.eu/api/vote.php?id=5151&amp;key=0		</voteinfo>
		<voteid>
			5151
		</voteid>
	</vote>
	<vote>
		<voteinfo>
			http://www.itsyourparliament.eu/api/vote.php?id=5152&amp;key=0		</voteinfo>
		<voteid>
			5152
		</voteid>
	</vote>
	<vote>
		<voteinfo>
			http://www.itsyourparliament.eu/api/vote.php?id=5153&amp;key=0		</voteinfo>
		<voteid>
			5153
		</voteid>
	</vote>
	<vote>
		<voteinfo>
			http://www.itsyourparliament.eu/api/vote.php?id=5154&amp;key=0		</voteinfo>
		<voteid>
			5154
		</voteid>
	</vote>
	<vote>
		<voteinfo>
			http://www.itsyourparliament.eu/api/vote.php?id=5155&amp;key=0		</voteinfo>
		<voteid>
			5155
		</voteid>
	</vote>
	<vote>
		<voteinfo>
			http://www.itsyourparliament.eu/api/vote.php?id=5156&amp;key=0		</voteinfo>
		<voteid>
			5156
		</voteid>
	</vote>
	<vote>
		<voteinfo>
			http://www.itsyourparliament.eu/api/vote.php?id=5157&amp;key=0		</voteinfo>
		<voteid>
			5157
		</voteid>
	</vote>
	<vote>
		<voteinfo>
			http://www.itsyourparliament.eu/api/vote.php?id=5158&amp;key=0		</voteinfo>
		<voteid>
			5158
		</voteid>
	</vote>
	<vote>
		<voteinfo>
			http://www.itsyourparliament.eu/api/vote.php?id=5159&amp;key=0		</voteinfo>
		<voteid>
			5159
		</voteid>
	</vote>
	<vote>
		<voteinfo>
			http://www.itsyourparliament.eu/api/vote.php?id=5225&amp;key=0		</voteinfo>
		<voteid>
			5225
		</voteid>
	</vote>
	<vote>
		<voteinfo>
			http://www.itsyourparliament.eu/api/vote.php?id=5226&amp;key=0		</voteinfo>
		<voteid>
			5226
		</voteid>
	</vote>
	<vote>
		<voteinfo>
			http://www.itsyourparliament.eu/api/vote.php?id=5227&amp;key=0		</voteinfo>
		<voteid>
			5227
		</voteid>
	</vote>
	<vote>
		<voteinfo>
			http://www.itsyourparliament.eu/api/vote.php?id=5228&amp;key=0		</voteinfo>
		<voteid>
			5228
		</voteid>
	</vote>
	<vote>
		<voteinfo>
			http://www.itsyourparliament.eu/api/vote.php?id=5229&amp;key=0		</voteinfo>
		<voteid>
			5229
		</voteid>
	</vote>
	<vote>
		<voteinfo>
			http://www.itsyourparliament.eu/api/vote.php?id=5230&amp;key=0		</voteinfo>
		<voteid>
			5230
		</voteid>
	</vote>
	<vote>
		<voteinfo>
			http://www.itsyourparliament.eu/api/vote.php?id=5231&amp;key=0		</voteinfo>
		<voteid>
			5231
		</voteid>
	</vote>
	<vote>
		<voteinfo>
			http://www.itsyourparliament.eu/api/vote.php?id=5232&amp;key=0		</voteinfo>
		<voteid>
			5232
		</voteid>
	</vote>
	<vote>
		<voteinfo>
			http://www.itsyourparliament.eu/api/vote.php?id=5233&amp;key=0		</voteinfo>
		<voteid>
			5233
		</voteid>
	</vote>
	<vote>
		<voteinfo>
			http://www.itsyourparliament.eu/api/vote.php?id=5241&amp;key=0		</voteinfo>
		<voteid>
			5241
		</voteid>
	</vote>
	<vote>
		<voteinfo>
			http://www.itsyourparliament.eu/api/vote.php?id=5386&amp;key=0		</voteinfo>
		<voteid>
			5386
		</voteid>
	</vote>
	<vote>
		<voteinfo>
			http://www.itsyourparliament.eu/api/vote.php?id=5692&amp;key=0		</voteinfo>
		<voteid>
			5692
		</voteid>
	</vote>
	<vote>
		<voteinfo>
			http://www.itsyourparliament.eu/api/vote.php?id=5693&amp;key=0		</voteinfo>
		<voteid>
			5693
		</voteid>
	</vote>
	<vote>
		<voteinfo>
			http://www.itsyourparliament.eu/api/vote.php?id=5694&amp;key=0		</voteinfo>
		<voteid>
			5694
		</voteid>
	</vote>
	<vote>
		<voteinfo>
			http://www.itsyourparliament.eu/api/vote.php?id=5781&amp;key=0		</voteinfo>
		<voteid>
			5781
		</voteid>
	</vote>
	<vote>
		<voteinfo>
			http://www.itsyourparliament.eu/api/vote.php?id=5895&amp;key=0		</voteinfo>
		<voteid>
			5895
		</voteid>
	</vote>
	<vote>
		<voteinfo>
			http://www.itsyourparliament.eu/api/vote.php?id=5905&amp;key=0		</voteinfo>
		<voteid>
			5905
		</voteid>
	</vote>
	<vote>
		<voteinfo>
			http://www.itsyourparliament.eu/api/vote.php?id=5936&amp;key=0		</voteinfo>
		<voteid>
			5936
		</voteid>
	</vote>
	<vote>
		<voteinfo>
			http://www.itsyourparliament.eu/api/vote.php?id=6046&amp;key=0		</voteinfo>
		<voteid>
			6046
		</voteid>
	</vote>
	<vote>
		<voteinfo>
			http://www.itsyourparliament.eu/api/vote.php?id=6047&amp;key=0		</voteinfo>
		<voteid>
			6047
		</voteid>
	</vote>
	<vote>
		<voteinfo>
			http://www.itsyourparliament.eu/api/vote.php?id=6048&amp;key=0		</voteinfo>
		<voteid>
			6048
		</voteid>
	</vote>
	<vote>
		<voteinfo>
			http://www.itsyourparliament.eu/api/vote.php?id=6049&amp;key=0		</voteinfo>
		<voteid>
			6049
		</voteid>
	</vote>
	<vote>
		<voteinfo>
			http://www.itsyourparliament.eu/api/vote.php?id=6050&amp;key=0		</voteinfo>
		<voteid>
			6050
		</voteid>
	</vote>
	<vote>
		<voteinfo>
			http://www.itsyourparliament.eu/api/vote.php?id=6051&amp;key=0		</voteinfo>
		<voteid>
			6051
		</voteid>
	</vote>
	<vote>
		<voteinfo>
			http://www.itsyourparliament.eu/api/vote.php?id=6052&amp;key=0		</voteinfo>
		<voteid>
			6052
		</voteid>
	</vote>
	<vote>
		<voteinfo>
			http://www.itsyourparliament.eu/api/vote.php?id=6053&amp;key=0		</voteinfo>
		<voteid>
			6053
		</voteid>
	</vote>
	<vote>
		<voteinfo>
			http://www.itsyourparliament.eu/api/vote.php?id=6054&amp;key=0		</voteinfo>
		<voteid>
			6054
		</voteid>
	</vote>
	<vote>
		<voteinfo>
			http://www.itsyourparliament.eu/api/vote.php?id=6055&amp;key=0		</voteinfo>
		<voteid>
			6055
		</voteid>
	</vote>
	<vote>
		<voteinfo>
			http://www.itsyourparliament.eu/api/vote.php?id=6056&amp;key=0		</voteinfo>
		<voteid>
			6056
		</voteid>
	</vote>
	<vote>
		<voteinfo>
			http://www.itsyourparliament.eu/api/vote.php?id=6057&amp;key=0		</voteinfo>
		<voteid>
			6057
		</voteid>
	</vote>
	<vote>
		<voteinfo>
			http://www.itsyourparliament.eu/api/vote.php?id=6058&amp;key=0		</voteinfo>
		<voteid>
			6058
		</voteid>
	</vote>
	<vote>
		<voteinfo>
			http://www.itsyourparliament.eu/api/vote.php?id=6059&amp;key=0		</voteinfo>
		<voteid>
			6059
		</voteid>
	</vote>
	<vote>
		<voteinfo>
			http://www.itsyourparliament.eu/api/vote.php?id=6060&amp;key=0		</voteinfo>
		<voteid>
			6060
		</voteid>
	</vote>
	<vote>
		<voteinfo>
			http://www.itsyourparliament.eu/api/vote.php?id=6061&amp;key=0		</voteinfo>
		<voteid>
			6061
		</voteid>
	</vote>
	<vote>
		<voteinfo>
			http://www.itsyourparliament.eu/api/vote.php?id=6062&amp;key=0		</voteinfo>
		<voteid>
			6062
		</voteid>
	</vote>
	<vote>
		<voteinfo>
			http://www.itsyourparliament.eu/api/vote.php?id=6063&amp;key=0		</voteinfo>
		<voteid>
			6063
		</voteid>
	</vote>
	<vote>
		<voteinfo>
			http://www.itsyourparliament.eu/api/vote.php?id=6064&amp;key=0		</voteinfo>
		<voteid>
			6064
		</voteid>
	</vote>
	<vote>
		<voteinfo>
			http://www.itsyourparliament.eu/api/vote.php?id=6156&amp;key=0		</voteinfo>
		<voteid>
			6156
		</voteid>
	</vote>
</votes>
