<?xml version="1.0" encoding="UTF-8"?>
<mepinfo>
	<mepid>
		346
	</mepid>
	<mepname>
		Saudargas
	</mepname>
	<fullname>
		Algirdas Saudargas
	</fullname>
	<country>
		Lithuania
	</country>
	<countryinfo>
		http://www.itsyourparliament.eu/api/country.php?id=7&amp;key=0
	</countryinfo>
	<title>
		Member
	</title>
	<party>
		Tėvynės sąjunga - Lietuvos krikščionys demokratai
	</party>
	<mepprofile>
		http://www.itsyourparliament.eu/meps/346.html

	</mepprofile>
	<webpage>
		
	</webpage>
	<address>
		Europos Parlamentas, Rue Wiertz, Altiero Spinelli 03F254, B-1047, Briuselyje
	</address>
	<mail>
		
	</mail>
	<birth>
		1948-04-17
	</birth>
	<birthplace>
		Kaunas
	</birthplace>
	<europarlid>
		96696
	</europarlid>
	<membersince>
		
	</membersince>
	<membertill>
		
	</membertill>
	<group>
		PPE
	</group>
	<attendance>
  		92	</attendance>

</mepinfo>
