<?xml version="1.0" encoding="UTF-8"?>
<mepinfo>
	<mepid>
		404
	</mepid>
	<mepname>
		Ek
	</mepname>
	<fullname>
		Lena Ek
	</fullname>
	<country>
		Sweden
	</country>
	<countryinfo>
		http://www.itsyourparliament.eu/api/country.php?id=14&amp;key=0
	</countryinfo>
	<title>
		Member of the Bureau
	</title>
	<party>
		Centerpartiet
	</party>
	<mepprofile>
		http://www.itsyourparliament.eu/meps/404.html

	</mepprofile>
	<webpage>
		http://www.lenaek.se
	</webpage>
	<address>
		Europaparlamentet, Rue Wiertz, Altiero Spinelli 10G342, B-1047, Bryssel
	</address>
	<mail>
		
	</mail>
	<birth>
		1958-01-16
	</birth>
	<birthplace>
		Mönsterås
	</birthplace>
	<europarlid>
		28127
	</europarlid>
	<membersince>
		
	</membersince>
	<membertill>
		
	</membertill>
	<group>
		ALDE
	</group>
	<attendance>
  		46	</attendance>

</mepinfo>
