<?xml version="1.0" encoding="UTF-8"?>
<mepinfo>
	<mepid>
		477
	</mepid>
	<mepname>
		Glattfelder
	</mepname>
	<fullname>
		Béla Glattfelder
	</fullname>
	<country>
		Hungary
	</country>
	<countryinfo>
		http://www.itsyourparliament.eu/api/country.php?id=16&amp;key=0
	</countryinfo>
	<title>
		Member
	</title>
	<party>
		Fidesz-Magyar Polgári Szövetség-Keresztény Demokrata Néppárt
	</party>
	<mepprofile>
		http://www.itsyourparliament.eu/meps/477.html

	</mepprofile>
	<webpage>
		
	</webpage>
	<address>
		Európai Parlament, Rue Wiertz, Altiero Spinelli 12E254, B-1047, Brüsszel
	</address>
	<mail>
		
	</mail>
	<birth>
		1967-05-04
	</birth>
	<birthplace>
		Budapest
	</birthplace>
	<europarlid>
		28145
	</europarlid>
	<membersince>
		
	</membersince>
	<membertill>
		
	</membertill>
	<group>
		PPE
	</group>
	<attendance>
  		93	</attendance>

</mepinfo>
