<?xml version="1.0" encoding="UTF-8"?>
<mepinfo>
	<mepid>
		67
	</mepid>
	<mepname>
		Neuser
	</mepname>
	<fullname>
		Norbert Neuser
	</fullname>
	<country>
		Germany
	</country>
	<countryinfo>
		http://www.itsyourparliament.eu/api/country.php?id=27&amp;key=0
	</countryinfo>
	<title>
		Member
	</title>
	<party>
		Sozialdemokratische Partei Deutschlands
	</party>
	<mepprofile>
		http://www.itsyourparliament.eu/meps/67.html

	</mepprofile>
	<webpage>
		
	</webpage>
	<address>
		Europäisches Parlament, Rue Wiertz, Altiero Spinelli 12G246, B-1047, Brüssel
	</address>
	<mail>
		
	</mail>
	<birth>
		1949-03-22
	</birth>
	<birthplace>
		Boppard
	</birthplace>
	<europarlid>
		96844
	</europarlid>
	<membersince>
		
	</membersince>
	<membertill>
		
	</membertill>
	<group>
		SD
	</group>
	<attendance>
  		92	</attendance>

</mepinfo>
